pyrifreg/__init__.py
pyrifreg/rif_generators.py
pyrifreg/rif_regression.py
pyrifreg-0.1.1.dist-info/licenses/LICENSE
pyrifreg-0.1.1.dist-info/METADATA
pyrifreg-0.1.1.dist-info/WHEEL
pyrifreg-0.1.1.dist-info/top_level.txt
pyrifreg-0.1.1.dist-info/RECORD
